MANIFEST.in
README.md
setup.py
multiprocessing_log_manager/__init__.py
multiprocessing_log_manager/log_manager.py
multiprocessing_log_manager.egg-info/PKG-INFO
multiprocessing_log_manager.egg-info/SOURCES.txt
multiprocessing_log_manager.egg-info/dependency_links.txt
multiprocessing_log_manager.egg-info/requires.txt
multiprocessing_log_manager.egg-info/top_level.txt
multiprocessing_log_manager/concurrent_log_handler/__init__.py
multiprocessing_log_manager/concurrent_log_handler/portalocker.py
multiprocessing_log_manager/concurrent_log_handler/queue.py